electronpy/__init__.py
electronpy/electron.py
electronpy/electron/LICENSE
electronpy/electron/LICENSES.chromium.html
electronpy/electron/chrome_100_percent.pak
electronpy/electron/chrome_200_percent.pak
electronpy/electron/d3dcompiler_47.dll
electronpy/electron/electron.exe
electronpy/electron/ffmpeg.dll
electronpy/electron/icudtl.dat
electronpy/electron/libEGL.dll
electronpy/electron/libGLESv2.dll
electronpy/electron/resources.pak
electronpy/electron/snapshot_blob.bin
electronpy/electron/v8_context_snapshot.bin
electronpy/electron/version
electronpy/electron/vk_swiftshader.dll
electronpy/electron/vk_swiftshader_icd.json
electronpy/electron/vulkan-1.dll
electronpy/electron/locales/am.pak
electronpy/electron/locales/ar.pak
electronpy/electron/locales/bg.pak
electronpy/electron/locales/bn.pak
electronpy/electron/locales/ca.pak
electronpy/electron/locales/cs.pak
electronpy/electron/locales/da.pak
electronpy/electron/locales/de.pak
electronpy/electron/locales/el.pak
electronpy/electron/locales/en-GB.pak
electronpy/electron/locales/en-US.pak
electronpy/electron/locales/es-419.pak
electronpy/electron/locales/es.pak
electronpy/electron/locales/et.pak
electronpy/electron/locales/fa.pak
electronpy/electron/locales/fi.pak
electronpy/electron/locales/fil.pak
electronpy/electron/locales/fr.pak
electronpy/electron/locales/gu.pak
electronpy/electron/locales/he.pak
electronpy/electron/locales/hi.pak
electronpy/electron/locales/hr.pak
electronpy/electron/locales/hu.pak
electronpy/electron/locales/id.pak
electronpy/electron/locales/it.pak
electronpy/electron/locales/ja.pak
electronpy/electron/locales/kn.pak
electronpy/electron/locales/ko.pak
electronpy/electron/locales/lt.pak
electronpy/electron/locales/lv.pak
electronpy/electron/locales/ml.pak
electronpy/electron/locales/mr.pak
electronpy/electron/locales/ms.pak
electronpy/electron/locales/nb.pak
electronpy/electron/locales/nl.pak
electronpy/electron/locales/pl.pak
electronpy-0.0.5.dist-info/DESCRIPTION.rst
electronpy-0.0.5.dist-info/METADATA
electronpy-0.0.5.dist-info/RECORD
electronpy-0.0.5.dist-info/WHEEL
electronpy-0.0.5.dist-info/entry_points.txt
electronpy-0.0.5.dist-info/metadata.json
electronpy-0.0.5.dist-info/top_level.txt
