Metadata-Version: 2.0
Name: electronpy
Version: 0.0.5
Summary: wrapper for electron
Home-page: https://gitee.com/yuncliu/electronpy
License: Apache
Platform: Windows
Platform: Linux
Classifier: Programming Language :: Python :: 3
Classifier: License :: OSI Approved :: Apache Software License
Classifier: Operating System :: OS Independent
Requires-Python: >= 3.6
